README
setup.py
nyanbar/__init__.py
nyanbar/nyanbar.py
nyanbar.egg-info/PKG-INFO
nyanbar.egg-info/SOURCES.txt
nyanbar.egg-info/dependency_links.txt
nyanbar.egg-info/top_level.txt