Metadata-Version: 1.0
Name: nyanbar
Version: 0.3
Summary: nyanbar is a progress bar for scripts that uses the Nyan cat instead of other stuff.
Home-page: https://github.com/apgwoz/nyanbar
Author: Andrew Gwozdziewycz
Author-email: web@apgwoz.com
License: LGPL
Platform: UNKNOWN
Classifier: License :: OSI Approved :: GNU Library or Lesser General Public License (LGPL)
Classifier: Environment :: Console
